ezff/__init__.py
ezff/errors.py
ezff/ffio.py
ezff/interfaces/__init__.py
ezff/interfaces/gaussian.py
ezff/interfaces/gulp.py
ezff/interfaces/lammps.py
ezff/interfaces/qchem.py
ezff/interfaces/rxmd.py
ezff/interfaces/vasp.py
ezff/utils/__init__.py
ezff/utils/atomic_properties.py
ezff/utils/convert_units.py
ezff/utils/reaxff.py
EZFF-1.0.11.dist-info/LICENSE
EZFF-1.0.11.dist-info/METADATA
EZFF-1.0.11.dist-info/WHEEL
EZFF-1.0.11.dist-info/top_level.txt
EZFF-1.0.11.dist-info/RECORD
