Metadata-Version: 2.1
Name: EZFF
Version: 1.0.11
Summary: Multiobjective forcefield optimization for Molecular Dynamics
Author: Aravind Krishnamoorthy
Author-email: arvk@users.noreply.github.com
License: MIT License
Classifier: Development Status :: 4 - Beta
Classifier: Intended Audience :: Science/Research
Classifier: License :: OSI Approved :: MIT License
Classifier: Programming Language :: Python :: 3.6
Classifier: Programming Language :: Python :: 3.7
Classifier: Topic :: Scientific/Engineering :: Chemistry
Classifier: Topic :: Scientific/Engineering :: Physics
Classifier: Natural Language :: English
Classifier: Operating System :: POSIX :: Linux
Classifier: Operating System :: Unix
License-File: LICENSE
Requires-Dist: numpy==1.26.4
Requires-Dist: mpi4py>=3.0.0
Requires-Dist: xtal>=0.9.1
Requires-Dist: schwimmbad>=0.3.2
Requires-Dist: nevergrad>=0.11.0
Requires-Dist: pymoo>=0.6.0.dev0
Requires-Dist: platypus-opt>=1.0.3
Requires-Dist: deap>=1.3.0
Requires-Dist: periodictable>=1.6.1
Requires-Dist: cclib>=1.8
